.gitignore
CHANGELOG.md
LICENSE
PKG-INFO
README.md
pyproject.toml
.github/actions/pylsp_bec_install/action.yml
.github/scripts/pr_issue_sync/pr_issue_sync.py
.github/scripts/pr_issue_sync/requirements.txt
.github/workflows/add-issues.yml
.github/workflows/check_pr.yml
.github/workflows/ci.yml
.github/workflows/formatter.yml
.github/workflows/pytest-matrix.yml
.github/workflows/pytest.yml
.github/workflows/semantic_release.yml
.github/workflows/sync-issues-pr.yml
pylsp_bec/__init__.py
pylsp_bec/_run_debug.py
pylsp_bec/completions.py
pylsp_bec/signatures.py
pylsp_bec/utils.py
pylsp_bec/workspace_changed.py
pylsp_bec-1.2.0.dist-info/METADATA
pylsp_bec-1.2.0.dist-info/WHEEL
pylsp_bec-1.2.0.dist-info/entry_points.txt
pylsp_bec-1.2.0.dist-info/licenses/LICENSE
pylsp_bec-1.2.0.dist-info/RECORD
